pathfinding3d/__init__.py
pathfinding3d/version.txt
pathfinding3d/core/__init__.py
pathfinding3d/core/diagonal_movement.py
pathfinding3d/core/grid.py
pathfinding3d/core/heap.py
pathfinding3d/core/heuristic.py
pathfinding3d/core/node.py
pathfinding3d/core/util.py
pathfinding3d/core/world.py
pathfinding3d/finder/__init__.py
pathfinding3d/finder/a_star.py
pathfinding3d/finder/best_first.py
pathfinding3d/finder/bi_a_star.py
pathfinding3d/finder/breadth_first.py
pathfinding3d/finder/dijkstra.py
pathfinding3d/finder/finder.py
pathfinding3d/finder/ida_star.py
pathfinding3d/finder/msp.py
pathfinding3d/finder/theta_star.py
pathfinding3d-0.7.2.dist-info/LICENSE
pathfinding3d-0.7.2.dist-info/METADATA
pathfinding3d-0.7.2.dist-info/WHEEL
pathfinding3d-0.7.2.dist-info/top_level.txt
pathfinding3d-0.7.2.dist-info/RECORD
