Metadata-Version: 2.1
Name: pathfinding3d
Version: 0.7.2
Summary: Pathfinding algorithms in 3D grids (based on python-pathfinding)
Home-page: https://github.com/harisankar95/pathfinding3D
Author: Harisankar Babu
License: MIT
Keywords: pathfinding,pathplanning,python,3D,A*,Dijkstra,Theta*
Platform: any
Classifier: Development Status :: 3 - Alpha
Classifier: License :: OSI Approved :: MIT License
Classifier: Natural Language :: English
Classifier: Operating System :: OS Independent
Classifier: Programming Language :: Python :: 3.8
Requires-Python: >=3.8
Provides-Extra: vis
Provides-Extra: dev
Provides-Extra: test
Provides-Extra: doc
